colour.py
color_science-0.4.5.dist-info/LICENSE
color_science-0.4.5.dist-info/METADATA
color_science-0.4.5.dist-info/WHEEL
color_science-0.4.5.dist-info/top_level.txt
color_science-0.4.5.dist-info/RECORD
