Metadata-Version: 2.1
Name: color-science
Version: 0.4.5
Summary: Protective placeholder package for 'color-science'. Please use 'colour-science' instead.
Home-page: https://pypi.org/project/color-science
Author: Jingyi Yang
Author-email: yangjingyi1210@gmail.com
License: MIT
Classifier: Programming Language :: Python
Classifier: License :: OSI Approved :: MIT License
Classifier: Operating System :: OS Independent
License-File: LICENSE
